LICENSE
MANIFEST.in
README.rst
bootstrap-buildout.py
buildout.cfg
requirements.txt
setup.py
version.txt
bob/__init__.py
bob.paper.btas_j2016.egg-info/PKG-INFO
bob.paper.btas_j2016.egg-info/SOURCES.txt
bob.paper.btas_j2016.egg-info/dependency_links.txt
bob.paper.btas_j2016.egg-info/entry_points.txt
bob.paper.btas_j2016.egg-info/not-zip-safe
bob.paper.btas_j2016.egg-info/requires.txt
bob.paper.btas_j2016.egg-info/top_level.txt
bob/paper/__init__.py
bob/paper/btas_j2016/__init__.py
bob/paper/btas_j2016/fuse_asv_pad_scores.py
bob/paper/btas_j2016/plot_det_from_sets.py
bob/paper/btas_j2016/plot_far_frr_pad.py
bob/paper/btas_j2016/plot_pad_results.py
doc/conf.py
doc/index.rst