Metadata-Version: 1.1
Name: bob.paper.btas-j2016
Version: 1.0.3
Summary: Package for BTAS 2016 paper on ASV-PAD systems
Home-page: https://gitlab.idiap.ch/bob/bob.paper.btas_j2016
Author: Pavel Korshunov
Author-email: pavel.korshunov@idiap.ch
License: BSD
Keywords: Bob package,BTAS 2016 paper,ASV and PAD systems
Platform: UNKNOWN
Classifier: Framework :: Bob
Classifier: Development Status :: 4 - Beta
Classifier: Intended Audience :: Science/Research
Classifier: License :: OSI Approved :: BSD License
Classifier: Natural Language :: English
Classifier: Programming Language :: Python
Classifier: Programming Language :: Python :: 3
Classifier: Topic :: Scientific/Engineering :: Artificial Intelligence
Classifier: Topic :: Database :: Front-Ends
